pulumi_mailgun/__init__.py
pulumi_mailgun/_inputs.py
pulumi_mailgun/_utilities.py
pulumi_mailgun/api_key.py
pulumi_mailgun/domain.py
pulumi_mailgun/domain_credential.py
pulumi_mailgun/get_domain.py
pulumi_mailgun/outputs.py
pulumi_mailgun/provider.py
pulumi_mailgun/pulumi-plugin.json
pulumi_mailgun/py.typed
pulumi_mailgun/route.py
pulumi_mailgun/webhook.py
pulumi_mailgun/config/__init__.py
pulumi_mailgun/config/__init__.pyi
pulumi_mailgun/config/vars.py
pulumi_mailgun-3.7.0.dist-info/METADATA
pulumi_mailgun-3.7.0.dist-info/WHEEL
pulumi_mailgun-3.7.0.dist-info/top_level.txt
pulumi_mailgun-3.7.0.dist-info/RECORD
